mkdocstrings_handlers/m_cli/__init__.py
mkdocstrings_handlers/m_cli/class_attr.py
mkdocstrings_handlers/m_cli/field_parser.py
mkdocstrings_handlers/m_cli/render_arg.py
mkdocstrings_m_cli-1.0.1.dist-info/LICENSE
mkdocstrings_m_cli-1.0.1.dist-info/METADATA
mkdocstrings_m_cli-1.0.1.dist-info/WHEEL
mkdocstrings_m_cli-1.0.1.dist-info/RECORD
