Metadata-Version: 2.1
Name: mkdocstrings-m_cli
Version: 1.0.1
Summary: A Python handler for mkdocstrings.
License: MIT
Author: Manuel Lopez
Author-email: jmlopez.rod@gmail.com
Requires-Python: >=3.10,<4.0
Classifier: License :: OSI Approved :: MIT License
Classifier: Programming Language :: Python :: 3
Classifier: Programming Language :: Python :: 3.10
Classifier: Programming Language :: Python :: 3.11
Requires-Dist: mkdocstrings-python (>=1.7.3,<2.0.0)
Requires-Dist: pydantic (>=2.1.0)
